liara/__init__.py
liara/client/__init__.py
liara/client/client.py
liara/errors/__init__.py
liara/errors/errors.py
liara/http/__init__.py
liara/http/api.py
liara/methods/__init__.py
liara/methods/apps/__init__.py
liara/methods/apps/create_app.py
liara/methods/apps/delete_app.py
liara/methods/apps/get_project.py
liara/methods/apps/get_projects.py
liara/methods/users/__init__.py
liara/methods/users/get_my_account.py
liara/methods/users/login.py
liara/types/__init__.py
liara/types/results.py
liara_cloud-2.0.dist-info/LICENSE
liara_cloud-2.0.dist-info/METADATA
liara_cloud-2.0.dist-info/WHEEL
liara_cloud-2.0.dist-info/top_level.txt
liara_cloud-2.0.dist-info/RECORD
