Metadata-Version: 2.1
Name: liara-cloud
Version: 2.0
Summary: Unofficial library for account management and services in Liara Cloud
Home-page: https://github.com/irvaniamirali/liara
Author: AmirAli Irvani
Author-email: irvaniamirali@proton.me
Keywords: liara,liara-cloud
Classifier: Programming Language :: Python :: 3.7
Classifier: Programming Language :: Python :: 3.8
Classifier: Programming Language :: Python :: 3.9
Classifier: Programming Language :: Python :: 3.10
Classifier: Programming Language :: Python :: 3.11
Classifier: Programming Language :: Python :: 3.12
Requires-Python: ~=3.7
License-File: LICENSE
Requires-Dist: requests
